{
  "id": 294686084,
  "cianId": 294686084,
  "dealType": "sale",
  "offerType": "flat",
  "category": "flatSale",
  "price": {
    "value": 1560000,
    "currency": "rur"
  },
  "offerInfo": {
    "saleType": "свободная продажа",
    "mortgage": "возможна ипотека"
  },
  "icons": [],
  "description": "Продaтcя уютная квaртиpа в прекрaснoм и экологически чиcтoм мecтечкe Пcкoвcкoй области, д. Хилово. Дом нахoдитcя в oчeнь удoбном мecтe! Pядoм находится ЛПУ \"Cанaтopий \"Хиловo\"(200м дo центрaльногo входа) В шаговoй дoступности магазин, банк, почтa. Прекpасноe сooбщeниe-пpямые автобусы, железнодорожная станция. Около 2 км-озеро. Квартира с достойным, свежим ремонтом!!!ДЕЛАЛИ ВС ДЛЯ СЕБЯ! Замена сантехники, электропроводки, труб, полов. Центральная горячая вода без перебоев. Полы:плитка, ламинат. Потолки натяжные с дополнительным освещением. Окна металлопластиковые. Железная дверь. Спутниковая антенна. Квартира очень тплая.ЗАХОДИ И ЖИВИ!Отличное предложение напрямую от собственника! Звоните, пишите, вс расскажу, напишу",
  "media": [
    {
      "url": "https://images.cdn-cian.ru/images/kvartira-hilovo-medicinskaya-ulica-2021700336-1.jpg",
      "previewUrl": "https://images.cdn-cian.ru/images/kvartira-hilovo-medicinskaya-ulica-2021700336-4.jpg",
      "type": "photo"
    },
    {
      "url": "https://images.cdn-cian.ru/images/kvartira-hilovo-medicinskaya-ulica-2021700332-1.jpg",
      "previewUrl": "https://images.cdn-cian.ru/images/kvartira-hilovo-medicinskaya-ulica-2021700332-4.jpg",
      "type": "photo"
    },
    {
      "url": "https://images.cdn-cian.ru/images/kvartira-hilovo-medicinskaya-ulica-2021700334-1.jpg",
      "previewUrl": "https://images.cdn-cian.ru/images/kvartira-hilovo-medicinskaya-ulica-2021700334-4.jpg",
      "type": "photo"
    },
    {
      "url": "https://images.cdn-cian.ru/images/kvartira-hilovo-medicinskaya-ulica-2021700337-1.jpg",
      "previewUrl": "https://images.cdn-cian.ru/images/kvartira-hilovo-medicinskaya-ulica-2021700337-4.jpg",
      "type": "photo"
    },
    {
      "url": "https://images.cdn-cian.ru/images/kvartira-hilovo-medicinskaya-ulica-2021700338-1.jpg",
      "previewUrl": "https://images.cdn-cian.ru/images/kvartira-hilovo-medicinskaya-ulica-2021700338-4.jpg",
      "type": "photo"
    },
    {
      "url": "https://images.cdn-cian.ru/images/kvartira-hilovo-medicinskaya-ulica-2021700341-1.jpg",
      "previewUrl": "https://images.cdn-cian.ru/images/kvartira-hilovo-medicinskaya-ulica-2021700341-4.jpg",
      "type": "photo"
    },
    {
      "url": "https://images.cdn-cian.ru/images/kvartira-hilovo-medicinskaya-ulica-2021700342-1.jpg",
      "previewUrl": "https://images.cdn-cian.ru/images/kvartira-hilovo-medicinskaya-ulica-2021700342-4.jpg",
      "type": "photo"
    }
  ],
  "photoLabel": {
    "color": "greenForOwner",
    "name": "Собственник"
  },
  "photoLabels": [
    {
      "color": "greenForOwner",
      "name": "Собственник"
    }
  ],
  "features": {
    "objectType": "1-комн. квартира",
    "totalArea": "31,8 м²",
    "floorInfo": "1/4 этаж"
  },
  "geo": {
    "regionId": 4605,
    "undergrounds": [],
    "highways": [],
    "address": [
      {
        "key": "location",
        "value": "Псковская область",
        "locationTypeId": 2
      },
      {
        "key": "location",
        "value": "Порховский муниципальный округ",
        "locationTypeId": 282
      },
      {
        "key": "location",
        "value": "д. Хилово",
        "locationTypeId": 161
      },
      {
        "key": "street",
        "value": "улица Медицинская"
      }
    ],
    "coordinates": {
      "lat": 57.773875,
      "lng": 29.383201
    },
    "timezone": 3
  },
  "gaLabel": "/sale/flat/mo_id=0/obl_id=4605/city_id=1222919/object_type=1/ga_obj_type=1/spec=none/294686084/from_developer=0/repres=0/owner=1/pod_snos=0/",
  "isPromoted": false,
  "isColorized": false,
  "puids": {
    "puid1": "deal_type_sale",
    "puid2": "offer_flat",
    "puid3": "sale_type_second",
    "puid4": "offer_type_1",
    "puid5": "obl_id_4605",
    "puid8": 1560000,
    "puid10": "no_agent",
    "puid16": "false",
    "puid17": "false",
    "puid36": 1219756
  },
  "phones": [
    "+79118905749",
    "+79118905757"
  ],
  "author": {
    "realtyId": 107759158,
    "cianId": 107759158,
    "id": "ID 107759158",
    "isHonest": false,
    "isPro": false,
    "isPartner": false,
    "agentAvailability": {
      "available": true,
      "userId": 107759158
    },
    "isChatsEnabled": true,
    "moderationInfo": {
      "showUserIdentifiedByDocuments": true
    }
  },
  "isFavorite": false,
  "additionalPrice": "49 057 ₽/м²",
  "newbuildingDynamicCalltracking": {},
  "fromImport": false,
  "isViewedOffer": false,
  "showWarningMessage": false,
  "isCalltrackingEnabled": true,
  "moderationInfo": {
    "showContactWarningMessage": false
  },
  "hasTour": false,
  "isExternalTourAvailable": false,
  "photoFeatureIcons": [],
  "isCianPartner": false,
  "isRosreestrChecked": false,
  "villageMortgageAllowed": false,
  "callButtonTitle": "Позвонить",
  "isBookedFromDeveloper": false
}