{
  "id": 309285632,
  "cianId": 309285632,
  "dealType": "sale",
  "offerType": "flat",
  "category": "flatSale",
  "price": {
    "value": 1500000,
    "currency": "rur"
  },
  "offerInfo": {
    "saleType": "свободная продажа"
  },
  "icons": [],
  "description": "Продам трехкомнатную квартиру в центре поселка Струги Красные.\nТребуется косметический ремонт.\nБольше вопросов по телефону.\nОсмотр по согласованию.\nВозможен торг.",
  "media": [
    {
      "url": "https://images.cdn-cian.ru/images/2311062243-1.jpg",
      "previewUrl": "https://images.cdn-cian.ru/images/2311062243-4.jpg",
      "type": "photo"
    },
    {
      "url": "https://images.cdn-cian.ru/images/2311067202-1.jpg",
      "previewUrl": "https://images.cdn-cian.ru/images/2311067202-4.jpg",
      "type": "photo"
    },
    {
      "url": "https://images.cdn-cian.ru/images/2311067200-1.jpg",
      "previewUrl": "https://images.cdn-cian.ru/images/2311067200-4.jpg",
      "type": "photo"
    },
    {
      "url": "https://images.cdn-cian.ru/images/2311050628-1.jpg",
      "previewUrl": "https://images.cdn-cian.ru/images/2311050628-4.jpg",
      "type": "photo"
    },
    {
      "url": "https://images.cdn-cian.ru/images/2311062356-1.jpg",
      "previewUrl": "https://images.cdn-cian.ru/images/2311062356-4.jpg",
      "type": "photo"
    },
    {
      "url": "https://images.cdn-cian.ru/images/2311062388-1.jpg",
      "previewUrl": "https://images.cdn-cian.ru/images/2311062388-4.jpg",
      "type": "photo"
    },
    {
      "url": "https://images.cdn-cian.ru/images/2311062184-1.jpg",
      "previewUrl": "https://images.cdn-cian.ru/images/2311062184-4.jpg",
      "type": "photo"
    },
    {
      "url": "https://images.cdn-cian.ru/images/2311062205-1.jpg",
      "previewUrl": "https://images.cdn-cian.ru/images/2311062205-4.jpg",
      "type": "photo"
    },
    {
      "url": "https://images.cdn-cian.ru/images/2311050651-1.jpg",
      "previewUrl": "https://images.cdn-cian.ru/images/2311050651-4.jpg",
      "type": "photo"
    },
    {
      "url": "https://images.cdn-cian.ru/images/2311062304-1.jpg",
      "previewUrl": "https://images.cdn-cian.ru/images/2311062304-4.jpg",
      "type": "photo"
    },
    {
      "url": "https://images.cdn-cian.ru/images/2311067204-1.jpg",
      "previewUrl": "https://images.cdn-cian.ru/images/2311067204-4.jpg",
      "type": "photo"
    },
    {
      "url": "https://images.cdn-cian.ru/images/2311062270-1.jpg",
      "previewUrl": "https://images.cdn-cian.ru/images/2311062270-4.jpg",
      "type": "photo"
    },
    {
      "url": "https://images.cdn-cian.ru/images/2311050652-1.jpg",
      "previewUrl": "https://images.cdn-cian.ru/images/2311050652-4.jpg",
      "type": "photo"
    },
    {
      "url": "https://images.cdn-cian.ru/images/2311062222-1.jpg",
      "previewUrl": "https://images.cdn-cian.ru/images/2311062222-4.jpg",
      "type": "photo"
    },
    {
      "url": "https://images.cdn-cian.ru/images/2311062159-1.jpg",
      "previewUrl": "https://images.cdn-cian.ru/images/2311062159-4.jpg",
      "type": "photo"
    },
    {
      "url": "https://images.cdn-cian.ru/images/2311062328-1.jpg",
      "previewUrl": "https://images.cdn-cian.ru/images/2311062328-4.jpg",
      "type": "photo"
    }
  ],
  "photoLabel": {
    "color": "greenForOwner",
    "name": "Собственник"
  },
  "photoLabels": [
    {
      "color": "blueOnlyCian",
      "name": "Только на Циан"
    },
    {
      "color": "greenForOwner",
      "name": "Собственник"
    }
  ],
  "features": {
    "objectType": "3-комн. квартира",
    "totalArea": "50 м²",
    "floorInfo": "1/2 этаж"
  },
  "geo": {
    "regionId": 4605,
    "undergrounds": [],
    "highways": [],
    "address": [
      {
        "key": "location",
        "value": "Псковская область",
        "locationTypeId": 2
      },
      {
        "key": "location",
        "value": "Струги Красные рп",
        "locationTypeId": 185
      }
    ],
    "coordinates": {
      "lat": 58.270527,
      "lng": 29.112404
    },
    "timezone": 3
  },
  "gaLabel": "/sale/flat/mo_id=0/obl_id=4605/city_id=473740/object_type=1/ga_obj_type=3/spec=none/309285632/from_developer=0/repres=0/owner=1/pod_snos=0/",
  "isPromoted": false,
  "isColorized": false,
  "puids": {
    "puid1": "deal_type_sale",
    "puid2": "offer_flat",
    "puid3": "sale_type_second",
    "puid4": "offer_type_3",
    "puid5": "obl_id_4605",
    "puid8": 1500000,
    "puid10": "no_agent",
    "puid16": "false",
    "puid17": "false",
    "puid36": 473740
  },
  "phones": [
    "+79212109312"
  ],
  "author": {
    "realtyId": 123907050,
    "cianId": 123907050,
    "id": "ID 123907050",
    "isHonest": false,
    "isPro": false,
    "isPartner": false,
    "agentAvailability": {
      "available": true,
      "userId": 123907050
    },
    "isChatsEnabled": true,
    "moderationInfo": {
      "showUserIdentifiedByDocuments": false
    }
  },
  "isFavorite": false,
  "additionalPrice": "30 000 ₽/м²",
  "newbuildingDynamicCalltracking": {},
  "fromImport": false,
  "isViewedOffer": false,
  "showWarningMessage": false,
  "isCalltrackingEnabled": true,
  "moderationInfo": {
    "showContactWarningMessage": false
  },
  "hasTour": false,
  "isExternalTourAvailable": false,
  "photoFeatureIcons": [],
  "isCianPartner": false,
  "isRosreestrChecked": false,
  "villageMortgageAllowed": false,
  "callButtonTitle": "Позвонить",
  "isBookedFromDeveloper": false
}