{
  "id": 304393518,
  "cianId": 304393518,
  "dealType": "sale",
  "offerType": "flat",
  "category": "flatSale",
  "price": {
    "value": 650000,
    "currency": "rur"
  },
  "offerInfo": {
    "saleType": "свободная продажа",
    "mortgage": "возможна ипотека"
  },
  "icons": [],
  "description": "Комнаты смежные, водоснабжение центральное, рабочий титан, отопление электрическое (тарифы как с электроплитами), один собственник, высокие перспективы газификации.\nПоселок в 25 км от г. Великие Луки, школа, ФАП с врачом, магазины, клуб, озеро, недалеко грибные и ягодные места, рыбалка.",
  "media": [
    {
      "url": "https://images.cdn-cian.ru/images/kvartira-poreche-2213533974-1.jpg",
      "previewUrl": "https://images.cdn-cian.ru/images/kvartira-poreche-2213533974-4.jpg",
      "type": "photo"
    },
    {
      "url": "https://images.cdn-cian.ru/images/kvartira-poreche-2213533968-1.jpg",
      "previewUrl": "https://images.cdn-cian.ru/images/kvartira-poreche-2213533968-4.jpg",
      "type": "photo"
    },
    {
      "url": "https://images.cdn-cian.ru/images/kvartira-poreche-2213533985-1.jpg",
      "previewUrl": "https://images.cdn-cian.ru/images/kvartira-poreche-2213533985-4.jpg",
      "type": "photo"
    },
    {
      "url": "https://images.cdn-cian.ru/images/kvartira-poreche-2213534023-1.jpg",
      "previewUrl": "https://images.cdn-cian.ru/images/kvartira-poreche-2213534023-4.jpg",
      "type": "photo"
    },
    {
      "url": "https://images.cdn-cian.ru/images/kvartira-poreche-2213534008-1.jpg",
      "previewUrl": "https://images.cdn-cian.ru/images/kvartira-poreche-2213534008-4.jpg",
      "type": "photo"
    },
    {
      "url": "https://images.cdn-cian.ru/images/kvartira-poreche-2213534379-1.jpg",
      "previewUrl": "https://images.cdn-cian.ru/images/kvartira-poreche-2213534379-4.jpg",
      "type": "photo"
    },
    {
      "url": "https://images.cdn-cian.ru/images/kvartira-poreche-2213534034-1.jpg",
      "previewUrl": "https://images.cdn-cian.ru/images/kvartira-poreche-2213534034-4.jpg",
      "type": "photo"
    },
    {
      "url": "https://images.cdn-cian.ru/images/kvartira-poreche-2213534015-1.jpg",
      "previewUrl": "https://images.cdn-cian.ru/images/kvartira-poreche-2213534015-4.jpg",
      "type": "photo"
    },
    {
      "url": "https://images.cdn-cian.ru/images/kvartira-poreche-2213533993-1.jpg",
      "previewUrl": "https://images.cdn-cian.ru/images/kvartira-poreche-2213533993-4.jpg",
      "type": "photo"
    },
    {
      "url": "https://images.cdn-cian.ru/images/kvartira-poreche-2213533980-1.jpg",
      "previewUrl": "https://images.cdn-cian.ru/images/kvartira-poreche-2213533980-4.jpg",
      "type": "photo"
    },
    {
      "url": "https://images.cdn-cian.ru/images/kvartira-poreche-2213534043-1.jpg",
      "previewUrl": "https://images.cdn-cian.ru/images/kvartira-poreche-2213534043-4.jpg",
      "type": "photo"
    }
  ],
  "photoLabels": [
    {
      "color": "blueOnlyCian",
      "name": "Только на Циан"
    }
  ],
  "features": {
    "objectType": "2-комн. квартира",
    "totalArea": "41,8 м²",
    "floorInfo": "2/2 этаж"
  },
  "geo": {
    "regionId": 4605,
    "undergrounds": [],
    "highways": [],
    "address": [
      {
        "key": "location",
        "value": "Псковская область",
        "locationTypeId": 2
      },
      {
        "key": "location",
        "value": "Великолукский район",
        "locationTypeId": 141
      },
      {
        "key": "location",
        "value": "Пореченская волость",
        "locationTypeId": 144
      },
      {
        "key": "location",
        "value": "д. Поречье",
        "locationTypeId": 161
      }
    ],
    "coordinates": {
      "lat": 56.095258,
      "lng": 30.482568
    },
    "timezone": 3
  },
  "gaLabel": "/sale/flat/mo_id=0/obl_id=4605/city_id=491728/object_type=1/ga_obj_type=2/spec=agent/304393518/from_developer=0/repres=0/owner=0/pod_snos=0/",
  "isPromoted": false,
  "isColorized": false,
  "puids": {
    "puid1": "deal_type_sale",
    "puid2": "offer_flat",
    "puid3": "sale_type_second",
    "puid4": "offer_type_2",
    "puid5": "obl_id_4605",
    "puid8": 650000,
    "puid10": "no_agent",
    "puid16": "false",
    "puid17": "false",
    "puid36": 491728
  },
  "phones": [
    "+79113514703"
  ],
  "author": {
    "realtyId": 94447266,
    "cianId": 94447266,
    "id": "ID 94447266",
    "isHonest": false,
    "isPro": false,
    "isPartner": false,
    "agentAvailability": {
      "available": true,
      "userId": 94447266
    },
    "isChatsEnabled": true,
    "agentLists": [],
    "qualityLevelInfo": {
      "levelSystemName": "high",
      "levelName": "Надёжный агент",
      "levelOrder": 3,
      "hasVerifiedDocuments": false,
      "highResponsibility": true
    },
    "moderationInfo": {
      "showUserIdentifiedByDocuments": false,
      "qualityLevelInfo": {
        "showSuperAgent": false,
        "showSuperHost": false,
        "showHighResponsibility": true
      }
    }
  },
  "isFavorite": false,
  "additionalPrice": "15 550 ₽/м²",
  "newbuildingDynamicCalltracking": {},
  "fromImport": false,
  "isViewedOffer": false,
  "showWarningMessage": false,
  "isCalltrackingEnabled": true,
  "moderationInfo": {
    "showContactWarningMessage": false
  },
  "hasTour": false,
  "isExternalTourAvailable": false,
  "photoFeatureIcons": [],
  "isCianPartner": false,
  "isRosreestrChecked": false,
  "villageMortgageAllowed": false,
  "callButtonTitle": "Позвонить",
  "isBookedFromDeveloper": false
}